odoo8_addon_marketing_security_group-8.0.1.0.0.99.dev6-py2.7-nspkg.pth
odoo8_addon_marketing_security_group-8.0.1.0.0.99.dev6.dist-info/DESCRIPTION.rst
odoo8_addon_marketing_security_group-8.0.1.0.0.99.dev6.dist-info/METADATA
odoo8_addon_marketing_security_group-8.0.1.0.0.99.dev6.dist-info/RECORD
odoo8_addon_marketing_security_group-8.0.1.0.0.99.dev6.dist-info/WHEEL
odoo8_addon_marketing_security_group-8.0.1.0.0.99.dev6.dist-info/metadata.json
odoo8_addon_marketing_security_group-8.0.1.0.0.99.dev6.dist-info/namespace_packages.txt
odoo8_addon_marketing_security_group-8.0.1.0.0.99.dev6.dist-info/top_level.txt
odoo_addons/marketing_security_group/README.rst
odoo_addons/marketing_security_group/__init__.py
odoo_addons/marketing_security_group/__openerp__.py
odoo_addons/marketing_security_group/i18n/de.po
odoo_addons/marketing_security_group/i18n/es.po
odoo_addons/marketing_security_group/i18n/fr.po
odoo_addons/marketing_security_group/i18n/marketing_security_group.pot
odoo_addons/marketing_security_group/i18n/sl.po
odoo_addons/marketing_security_group/security/ir.model.access.csv
odoo_addons/marketing_security_group/security/mail_mass_mailing_security.xml
odoo_addons/marketing_security_group/static/description/icon.png
odoo_addons/marketing_security_group/wizards/__init__.py
odoo_addons/marketing_security_group/wizards/test_mailing.py
